[{"mgr_id":"M0001","name":"Jacob","dob":"1990-08-22T18:30:00.000Z","team_id":"T0001","since":"2020-06-21T18:30:00.000Z"},{"mgr_id":"M0002","name":"Scott","dob":"1985-05-01T18:30:00.000Z","team_id":"T0002","since":"2021-03-21T18:30:00.000Z"},{"mgr_id":"M0003","name":"Brandon","dob":"1995-02-14T18:30:00.000Z","team_id":"T0003","since":"2019-04-01T18:30:00.000Z"},{"mgr_id":"M0004","name":"Jack","dob":"1987-01-24T18:30:00.000Z","team_id":"T0004","since":"2018-03-10T18:30:00.000Z"},{"mgr_id":"M0005","name":"Adom","dob":"1991-02-16T18:30:00.000Z","team_id":"T0005","since":"2020-02-14T18:30:00.000Z"},{"mgr_id":"M0006","name":"Philip","dob":"1989-10-03T18:30:00.000Z","team_id":"T0006","since":"2021-05-15T18:30:00.000Z"}]